[
    {
        "name": "亞皆老街近染布房街",
        "url": "http://tdcctv.data.one.gov.hk/K202F.JPG"
    },
    {
        "name": "界限街近大坑東道",
        "url": "http://tdcctv.data.one.gov.hk/K209F.JPG"
    },
    {
        "name": "廣東道近中港城",
        "url": "http://tdcctv.data.one.gov.hk/K104F.JPG"
    },
    {
        "name": "漆咸道近柯士甸道",
        "url": "http://tdcctv.data.one.gov.hk/K106F.JPG"
    },
    {
        "name": "漆咸道近公主道",
        "url": "http://tdcctv.data.one.gov.hk/K109F.JPG"
    },
    {
        "name": "櫻桃街近海泓道",
        "url": "http://tdcctv.data.one.gov.hk/K221F.JPG"
    },
    {
        "name": "長沙灣道近光昌街",
        "url": "http://tdcctv.data.one.gov.hk/K305F.JPG"
    },
    {
        "name": "呈祥道近明愛醫院",
        "url": "http://tdcctv.data.one.gov.hk/K802F.JPG"
    },
    {
        "name": "翠嶺路近寶順路",
        "url": "http://tdcctv.data.one.gov.hk/TK110F.JPG"
    },
    {
        "name": "清水灣道近飛鵝山道",
        "url": "http://tdcctv.data.one.gov.hk/K627F.JPG"
    },
    {
        "name": "海底隧道九龍入口",
        "url": "http://tdcctv.data.one.gov.hk/K107F.JPG"
    },
    {
        "name": "佐敦道近渡船街",
        "url": "http://tdcctv.data.one.gov.hk/K108F.JPG"
    },
    {
        "name": "啟祥道近宏照道",
        "url": "http://tdcctv.data.one.gov.hk/K613F.JPG"
    },
    {
        "name": "啟德隧道九龍城入口",
        "url": "http://tdcctv.data.one.gov.hk/K404F.JPG"
    },
    {
        "name": "葵涌道近美孚新邨",
        "url": "http://tdcctv.data.one.gov.hk/K325F.JPG"
    },
    {
        "name": "觀塘繞道近啟祥道",
        "url": "http://tdcctv.data.one.gov.hk/K814F.JPG"
    },
    {
        "name": "觀塘繞道近麗港城",
        "url": "http://tdcctv.data.one.gov.hk/K812F.JPG"
    },
    {
        "name": "觀塘繞道近勵業街",
        "url": "http://tdcctv.data.one.gov.hk/K813F.JPG"
    },
    {
        "name": "觀塘道近啟業邨",
        "url": "http://tdcctv.data.one.gov.hk/K621F.JPG"
    },
    {
        "name": "觀塘道近九龍灣港鐵站",
        "url": "http://tdcctv.data.one.gov.hk/K809F2.JPG"
    },
    {
        "name": "觀塘道近牛頭角港鐵站",
        "url": "http://tdcctv.data.one.gov.hk/K810F.JPG"
    },
    {
        "name": "鯉魚門道近茶果嶺道",
        "url": "http://tdcctv.data.one.gov.hk/K602F.JPG"
    },
    {
        "name": "龍翔道近澤安邨",
        "url": "http://tdcctv.data.one.gov.hk/K804F.JPG"
    },
    {
        "name": "龍翔道/竹園道",
        "url": "http://tdcctv.data.one.gov.hk/K505F.JPG"
    },
    {
        "name": "龍翔道/清水灣道",
        "url": "http://tdcctv.data.one.gov.hk/K614F.JPG"
    },
    {
        "name": "龍翔道/蒲崗村道",
        "url": "http://tdcctv.data.one.gov.hk/K508F.JPG"
    },
    {
        "name": "馬頭圍道近農圃道",
        "url": "http://tdcctv.data.one.gov.hk/K405F.JPG"
    },
    {
        "name": "彌敦道近荔枝角道",
        "url": "http://tdcctv.data.one.gov.hk/K205F.JPG"
    },
    {
        "name": "寶琳北路近寶康路",
        "url": "http://tdcctv.data.one.gov.hk/TK101F.JPG"
    },
    {
        "name": "寶順路近將軍澳游泳池",
        "url": "http://tdcctv.data.one.gov.hk/TK105F.JPG"
    },
    {
        "name": "太子道西天橋近世運公園",
        "url": "http://tdcctv.data.one.gov.hk/K506F.JPG"
    },
    {
        "name": "太子道東近新蒲崗",
        "url": "http://tdcctv.data.one.gov.hk/K521F.JPG"
    },
    {
        "name": "公主道近京士柏",
        "url": "http://tdcctv.data.one.gov.hk/K123F.JPG"
    },
    {
        "name": "公主道/亞皆老街",
        "url": "http://tdcctv.data.one.gov.hk/K409F.JPG"
    },
    {
        "name": "公主道/培正道",
        "url": "http://tdcctv.data.one.gov.hk/K408F.JPG"
    },
    {
        "name": "梳士巴利道近漆咸道",
        "url": "http://tdcctv.data.one.gov.hk/K102F.JPG"
    },
    {
        "name": "梳士巴利道近彌敦道",
        "url": "http://tdcctv.data.one.gov.hk/K101F.JPG"
    },
    {
        "name": "秀茂坪道近協和街",
        "url": "http://tdcctv.data.one.gov.hk/K607F.JPG"
    },
    {
        "name": "將軍澳道近翠屏南邨",
        "url": "http://tdcctv.data.one.gov.hk/K811F.JPG"
    },
    {
        "name": "將軍澳隧道將軍澳入口",
        "url": "http://tdcctv.data.one.gov.hk/TK904F.JPG"
    },
    {
        "name": "窩打老道/渡船街",
        "url": "http://tdcctv.data.one.gov.hk/K111F.JPG"
    },
    {
        "name": "窩打老道近東方街",
        "url": "http://tdcctv.data.one.gov.hk/K112F.JPG"
    },
    {
        "name": "窩打老道/歌和老街",
        "url": "http://tdcctv.data.one.gov.hk/K502F.JPG"
    },
    {
        "name": "西九龍走廊近南昌邨",
        "url": "http://tdcctv.data.one.gov.hk/K816F.JPG"
    },
    {
        "name": "西九龍公路近荔灣交匯處",
        "url": "http://tdcctv.data.one.gov.hk/K914F.JPG"
    },
    {
        "name": "西九龍公路油麻地北交匯處",
        "url": "http://tdcctv.data.one.gov.hk/K911F.JPG"
    },
    {
        "name": "西區海底隧道九龍入口",
        "url": "http://tdcctv.data.one.gov.hk/K901F.JPG"
    },
    {
        "name": "大老山隧道九龍入口",
        "url": "http://tdcctv.data.one.gov.hk/K931F.JPG"
    },
    {
        "name": "東區海底隧道九龍入口",
        "url": "http://tdcctv.data.one.gov.hk/K952F.JPG"
    },
    {
        "name": "廣東道近梳士巴利道",
        "url": "http://tdcctv.data.one.gov.hk/K121F.JPG"
    }
]
